{
    "fluentMethods": true,
    "clientRootFolder": "",
    "relationships": [],
    "fields": [
        {
            "fieldName": "name",
            "fieldType": "String",
            "fieldValidateRules": []
        },
        {
            "fieldName": "lastName",
            "fieldType": "String",
            "fieldValidateRules": []
        }
    ],
    "changelogDate": "20190321102035",
    "dto": "mapstruct",
    "searchEngine": false,
    "service": "serviceImpl",
    "entityTableName": "person",
    "jpaMetamodelFiltering": false,
    "pagination": "pagination",
    "microserviceName": "microserviziApp"
}
